src/__init__.py
src/bump_version.py
src/cli.py
src/helpers.py
bump_version_pep440-0.0.4.post1.dist-info/LICENSE.md
bump_version_pep440-0.0.4.post1.dist-info/METADATA
bump_version_pep440-0.0.4.post1.dist-info/WHEEL
bump_version_pep440-0.0.4.post1.dist-info/entry_points.txt
bump_version_pep440-0.0.4.post1.dist-info/RECORD
