Metadata-Version: 2.1
Name: bump-version-pep440
Version: 0.0.4.post1
Summary: Version-bump your software with a single command
Home-page: https://github.com/azataiot/bump-version-pep440
Author: Azat
Author-email: 8280770+azataiot@users.noreply.github.com
Requires-Python: >=3.9,<4.0
Classifier: Programming Language :: Python :: 3
Classifier: Programming Language :: Python :: 3.9
Classifier: Programming Language :: Python :: 3.10
Classifier: Programming Language :: Python :: 3.11
Requires-Dist: packaging (>=23.1,<24.0)
Requires-Dist: toml (>=0.10.2,<0.11.0)
Requires-Dist: typer[all] (>=0.9.0,<0.10.0)
